{
    "0": "\u2d57",
    "1": "\u237f",
    "2": "\u2056",
    "3": "\u2214",
    "4": "\u2299",
    "5": "\u22f5",
    "6": "\u25ec",
    "7": "\u2686",
    "8": "\u27c7",
    "9": "\u27d0",
    "10": "\u27d3",
    "11": "\u27d4",
    "12": "\ud804\udc10",
    "13": "\u2a00",
    "14": "\u2a03",
    "15": "\u2a25",
    "16": "\u2a30",
    "17": "\u2a40",
    "18": "\u2abd",
    "19": "\u2abe",
    "20": "\u2ac3",
    "21": "\u2ac4",
    "22": "\u2e2c",
    "23": "\u2e2d",
    "24": "\ua10d",
    "25": "\ua73e",
    "26": "\ud800\udd01",
    "27": "\u233d",
    "28": "\u233e",
    "29": "\u2349",
    "30": "\u235c",
    "31": "\u23c0",
    "32": "\u23c1",
    "33": "\u1367",
    "34": "\u23c2",
    "35": "\u23e3",
    "36": "\u25f5",
    "37": "\u25f6",
    "38": "\u2941",
    "39": "\u29b2",
    "40": "\u29b5",
    "41": "\u29ba",
    "42": "\u29c2",
    "43": "\u29f2",
    "44": "\u2a2d",
    "45": "\u2a2e",
    "46": "\u2b30",
    "47": "\u2b57",
    "48": "\u2b58",
    "49": "\ud805\uddd8",
    "50": "\ud834\udf07",
    "51": "\ud83d\udd41",
    "52": "\ud809\udc62",
    "53": "\ud809\udc70",
    "54": "\u22be",
    "55": "\u2991",
    "56": "\u2992",
    "57": "\u299d",
    "58": "\u2e01",
    "59": "\u2e16",
    "60": "\ud806\ude3f",
    "61": "\ud806\ude46",
    "62": "\ud806\ude43",
    "63": "\u2442",
    "64": "\u2443",
    "65": "\ua27d",
    "66": "\u1aa5",
    "67": "\u1aa4",
    "68": "\u1aa3",
    "69": "\ud807\udd08",
    "70": "\u237b",
    "71": "\ua95f",
    "72": "\ud804\udd43",
    "73": "\ud805\uddc9",
    "74": "\ud805\uddcc",
    "75": "\ud807\udc6c",
    "76": "\u07f9",
    "77": "\u1696",
    "78": "\u2d31",
    "79": "\u2d32",
    "80": "\u2d33",
    "81": "\u2d34",
    "82": "\u2d35",
    "83": "\u2d36",
    "84": "\u2d37",
    "85": "\u2d38",
    "86": "\u2d39",
    "87": "\u2d3a",
    "88": "\u2d3c",
    "89": "\u2d3d",
    "90": "\u2d3e",
    "91": "\u2d3f",
    "92": "\u2d40",
    "93": "\u2d41",
    "94": "\u2d43",
    "95": "\u2d44",
    "96": "\u2d45",
    "97": "\u2d46",
    "98": "\u2d47",
    "99": "\u2d48",
    "100": "\u2d49",
    "101": "\u2d4a",
    "102": "\u2d4b",
    "103": "\u2d4c",
    "104": "\u2d4d",
    "105": "\u2d4e",
    "106": "\u2d50",
    "107": "\u2d52",
    "108": "\u2d53",
    "109": "\u2d56",
    "110": "\u22a1",
    "111": "\u2d58",
    "112": "\u2d59",
    "113": "\u2d5a",
    "114": "\u2d5b",
    "115": "\u2d5c",
    "116": "\u2d5d",
    "117": "\u2d5e",
    "118": "\u2d5f",
    "119": "\u2d60",
    "120": "\u2d61",
    "121": "\u2d62",
    "122": "\u2d63",
    "123": "\u2d64",
    "124": "\u2d65",
    "125": "\u2d66",
    "126": "\u29ca",
    "127": "\ua943",
    "128": "\u22d6",
    "129": "\u22d7",
    "130": "\u276e",
    "131": "\u276f",
    "132": "\u2a7f",
    "133": "\u2a80",
    "134": "\u2a97",
    "135": "\u2a98",
    "136": "\u169b",
    "137": "\u169c",
    "138": "\u29a4",
    "139": "\u29a5",
    "140": "\u2948",
    "141": "\u2949",
    "142": "\u2a51",
    "143": "\u2a52",
    "144": "\u29a1",
    "145": "\u29a2",
    "146": "\u29a3",
    "147": "\u2cb4",
    "148": "\ud800\udf1e",
    "149": "\ud800\udf60",
    "150": "\ud801\udcb1",
    "151": "\u200B"
}